pysaten/__init__.py
pysaten/py.typed
pysaten/pysaten.py
pysaten/utility/WavLabHandler.py
pysaten/utility/color_noise.py
pysaten/utility/constants.py
pysaten/utility/signal.py
pysaten/v1/__init__.py
pysaten/v2/__init__.py
pysaten-2.2.2.dist-info/entry_points.txt
pysaten-2.2.2.dist-info/licenses/COPYING
pysaten-2.2.2.dist-info/WHEEL
pysaten-2.2.2.dist-info/METADATA
pysaten-2.2.2.dist-info/RECORD
