Metadata-Version: 2.4
Name: pysaten
Version: 2.2.2
Summary: Detect silence segment from speech signal.
Author-email: Fumiyoshi MATANO <fumiyoshi.matano@gmail.com>
Requires-Python: >=3.10
Classifier: Programming Language :: Python :: 3 :: Only
Classifier: License :: OSI Approved :: GNU General Public License v3 or later (GPLv3+)
License-File: COPYING
Requires-Dist: numpy>=1.20
Requires-Dist: noisereduce
Requires-Dist: librosa
Requires-Dist: soundfile
Requires-Dist: scipy
Project-URL: Repository, https://gitlab.com/f-matano44/pysaten.git
